setup.py
pysecurity/__init__.py
pysecurity/__main__.py
pysecurity/utils.py
pysecurity.egg-info/PKG-INFO
pysecurity.egg-info/SOURCES.txt
pysecurity.egg-info/dependency_links.txt
pysecurity.egg-info/top_level.txt