Metadata-Version: 2.1
Name: pysecurity
Version: 1.0.0
Summary: pysecurity Project
Home-page: https://github.com/pysecurity/pysecurity
Author: pysecurity
Author-email: pysecurity@gmail.com
License: UNKNOWN
Platform: UNKNOWN
